docker_dev-1.0a7.dist-info/pbr.json
docker_dev-1.0a7.dist-info/WHEEL
docker_dev-1.0a7.dist-info/metadata.json
docker_dev-1.0a7.dist-info/DESCRIPTION.rst
docker_dev-1.0a7.dist-info/METADATA
docker_dev-1.0a7.dist-info/top_level.txt
docker_dev-1.0a7.dist-info/entry_points.txt
docker_dev-1.0a7.dist-info/RECORD
docker_dev/__init__.py
docker_dev/projects.py
docker_dev/cli.py
docker_dev/subprocess.py
docker_dev/docker_interface.py
docker_dev/_logging.py
docker_dev/exceptions.py
docker_dev/plugins/__init__.py
docker_dev/plugins/git_integration.py
