Metadata-Version: 2.0
Name: docker-dev
Version: 1.0a7
Summary: Development tools for Docker
Home-page: https://github.com/2degrees/docker-dev
Author: 2degrees
Author-email: 2degrees-floss@googlegroups.com
License: UNKNOWN
Platform: UNKNOWN
Requires-Dist: click (==6.6)
Requires-Dist: PyYAML (==3.11)
